fastsyftbox/__init__.py
fastsyftbox/cli.py
fastsyftbox/constants.py
fastsyftbox/direct_http_transport.py
fastsyftbox/fastsyftbox.py
fastsyftbox/http_bridge.py
fastsyftbox/simple_client.py
fastsyftbox/transport.py
fastsyftbox/app_template/app.py
fastsyftbox/app_template/requirements.txt
fastsyftbox/app_template/run.sh
fastsyftbox/app_template/assets/rpc-debug.html
fastsyftbox/app_template/assets/css/rpc-debug.css
fastsyftbox/app_template/assets/js/rpc-debug.js
fastsyftbox/app_template/assets/js/syftbox-sdk.js
fastsyftbox-0.1.21.dist-info/METADATA
fastsyftbox-0.1.21.dist-info/WHEEL
fastsyftbox-0.1.21.dist-info/entry_points.txt
fastsyftbox-0.1.21.dist-info/licenses/LICENSE
fastsyftbox-0.1.21.dist-info/RECORD
